iris_interface/IrisInterfaceStatus.py
iris_interface/IrisModuleInterface.py
iris_interface/__init__.py
iris_interface-1.2.0.dist-info/LICENSE.txt
iris_interface-1.2.0.dist-info/METADATA
iris_interface-1.2.0.dist-info/WHEEL
iris_interface-1.2.0.dist-info/top_level.txt
iris_interface-1.2.0.dist-info/RECORD
