Metadata-Version: 2.1
Name: iris_interface
Version: 1.2.0
Summary: An interface for Iris modules
Home-page: https://github.com/dfir-iris/iris-module-interface
Author: DFIR-IRIS
Author-email: contact@dfir-iris.org
License: UNKNOWN
Platform: UNKNOWN
Classifier: Programming Language :: Python :: 3
Classifier: License :: OSI Approved :: GNU Lesser General Public License v3 (LGPLv3)
Classifier: Operating System :: OS Independent
License-File: LICENSE.txt
